Verilog/fulladder.v
module fulladder(input A,input B,input C_in,output S,output C);
   wire S_inter;
   wire C_inter1;
   wire C_inter2;
   xor(S_inter,A,B);
   xor(S,S_inter,C_in);
   and(C_inter1,A,B);
   and(C_inter2,S_inter,C_in);
   or(C,C_inter1,C_inter2);

endmodule

Verilog/addersubtractor.v
`include "fulladder.v"
module addersubtractor(input M,input [3:0] A,input [3:0] B,output [3:0] S,output carry);
  wire [3:0] B_updated;
  xor(B_updated[3],B[3],M);
  xor(B_updated[2],B[2],M);
  xor(B_updated[1],B[1],M);
  xor(B_updated[0],B[0],M);
  wire C1;
  wire C2;
  wire C3;
  fulladder instance_1(.A(A[0]),.B(B_updated[0]),.C_in(M),.S(S[0]),.C(C1));
  fulladder instance_2(.A(A[1]),.B(B_updated[1]),.C_in(C1),.S(S[1]),.C(C2));
  fulladder instance_3(.A(A[2]),.B(B_updated[2]),.C_in(C2),.S(S[2]),.C(C3));
  fulladder instance_4(.A(A[3]),.B(B_updated[3]),.C_in(C3),.S(S[3]),.C(carry));
  
endmodule

Verilog/addersubtractor_tb.v
`include "addersubtractor.v"
module addersubtractor_tb;
  reg [3:0] A;
  reg [3:0] B;
  reg M;
  wire [3:0] S;
  wire carry;
  addersubtractor DUT(M,A,B,S,carry);
  
  
  initial begin
    $dumpfile("addersubtractor_tb.vcd");
    $dumpvars(0, addersubtractor_tb);
    M=0;
    A=4'b0101;
    B=4'b1001;
    #10
    M=1;
    A=4'b0100;
    B=4'b1011;
    #10
    M=0;
    A=4'b0000;
    B=4'b1111;
    #10
    M=0;
    A=4'b0110;
    B=4'b1101;
    #10
    M=1;
    A=4'b1000;
    B=4'b1000;
    #10
    M=1;
    A=4'b0101;
    B=4'b1100;
    #10
    M=1;
    A=4'b0000;
    B=4'b1001;
    #10
    M=0;
    A=4'b0011;
    B=4'b1100;

    #10 $finish; 
  end
  
endmodule

Verilog/addersubtractor_tb.vcd
$date
	Mon Nov  6 19:35:28 2023
$end
$version
	Icarus Verilog
$end
$timescale
	1s
$end
$scope module addersubtractor_tb $end
$var wire 1 ! carry $end
$var wire 4 " S [3:0] $end
$var reg 4 # A [3:0] $end
$var reg 4 $ B [3:0] $end
$var reg 1 % M $end
$scope module DUT $end
$var wire 4 & A [3:0] $end
$var wire 4 ' B [3:0] $end
$var wire 1 % M $end
$var wire 1 ! carry $end
$var wire 4 ( S [3:0] $end
$var wire 1 ) C3 $end
$var wire 1 * C2 $end
$var wire 1 + C1 $end
$var wire 4 , B_updated [3:0] $end
$scope module instance_1 $end
$var wire 1 - A $end
$var wire 1 . B $end
$var wire 1 + C $end
$var wire 1 % C_in $end
$var wire 1 / C_inter1 $end
$var wire 1 0 C_inter2 $end
$var wire 1 1 S $end
$var wire 1 2 S_inter $end
$upscope $end
$scope module instance_2 $end
$var wire 1 3 A $end
$var wire 1 4 B $end
$var wire 1 * C $end
$var wire 1 + C_in $end
$var wire 1 5 C_inter1 $end
$var wire 1 6 C_inter2 $end
$var wire 1 7 S $end
$var wire 1 8 S_inter $end
$upscope $end
$scope module instance_3 $end
$var wire 1 9 A $end
$var wire 1 : B $end
$var wire 1 ) C $end
$var wire 1 * C_in $end
$var wire 1 ; C_inter1 $end
$var wire 1 < C_inter2 $end
$var wire 1 = S $end
$var wire 1 > S_inter $end
$upscope $end
$scope module instance_4 $end
$var wire 1 ? A $end
$var wire 1 @ B $end
$var wire 1 ! C $end
$var wire 1 ) C_in $end
$var wire 1 A C_inter1 $end
$var wire 1 B C_inter2 $end
$var wire 1 C S $end
$var wire 1 D S_inter $end
$upscope $end
$upscope $end
$upscope $end
$enddefinitions $end
#0
$dumpvars
1D
1C
0B
0A
1@
0?
1>
1=
0<
0;
0:
19
08
17
06
05
04
03
02
01
00
1/
1.
1-
b1001 ,
1+
0*
0)
b1110 (
b1001 '
b101 &
0%
b1001 $
b101 #
b1110 "
0!
$end
#10
07
0=
1)
0+
0D
0>
1;
08
0/
0@
1:
04
0.
0-
b100 ,
b1001 "
b1001 (
11
b1011 $
b1011 '
b100 #
b100 &
1%
#20
1=
1>
17
0)
1D
18
12
0;
1@
1:
14
1.
09
b1111 ,
b1111 "
b1111 (
11
b1111 $
b1111 '
b0 #
b0 &
0%
#30
1!
0C
1B
04
17
0*
b11 "
b11 (
0=
1)
b1101 ,
18
05
0>
1;
13
19
b1101 $
b1101 '
b110 #
b110 &
#40
0=
1!
1<
1>
0C
1B
1*
1)
12
07
16
0;
0@
1:
14
1.
1+
03
09
1?
b111 ,
b0 "
b0 (
01
10
b1000 $
b1000 '
b1000 #
b1000 &
1%
#50
1)
0!
0:
11
00
0=
1<
b1001 "
b1001 (
1C
0B
b11 ,
02
1/
1>
0;
0D
1-
19
0?
b1100 $
b1100 '
b101 #
b101 &
#60
0*
0C
17
06
0)
1:
0.
11
00
0+
b111 "
b111 (
1=
0<
b110 ,
02
0/
1>
0-
09
b1001 $
b1001 '
b0 #
b0 &
#70
0!
0B
0)
0<
0*
12
17
06
1C
1=
0+
1D
1>
0/
1@
1:
04
0.
1-
13
b1100 ,
b1111 "
b1111 (
11
b1100 $
b1100 '
b11 #
b11 &
0%
