Verilog/andblock.v
module andblock(input [3:0] A,input [3:0] B,output [3:0] C);
  and(C[3],A[3],B[3]);
  and(C[2],A[2],B[2]);
  and(C[1],A[1],B[1]);
  and(C[0],A[0],B[0]);
endmodule

Verilog/comparator.v
module comparator(input [3:0] A,input [3:0] B,output greater,output lesser,output equal);
  wire eq0;
  wire eq1;
  wire eq2;
  wire eq3;
  xnor(eq0,A[0],B[0]);
  xnor(eq1,A[1],B[1]);
  xnor(eq2,A[2],B[2]);
  xnor(eq3,A[3],B[3]);

  
  wire [3:0] A_comp;
  wire [3:0] B_comp;
  not(A_comp[3],A[3]);
  not(A_comp[2],A[2]);
  not(A_comp[1],A[1]);
  not(A_comp[0],A[0]);
  not(B_comp[3],B[3]);
  not(B_comp[2],B[2]);
  not(B_comp[1],B[1]);
  not(B_comp[0],B[0]);


  wire greater0;
  wire greater1;
  wire greater2;
  wire greater3;
  and(greater3,A[3],B_comp[3]);
  and(greater2,eq3,A[2],B_comp[2]);
  and(greater1,eq3,eq2,A[1],B_comp[1]);
  and(greater0,eq3,eq2,eq1,A[0],B_comp[0]);

 
  wire lesser0;
  wire lesser1;
  wire lesser2;
  wire lesser3;
  and(lesser3,A_comp[3],B[3]);
  and(lesser2,eq3,A_comp[2],B[2]);
  and(lesser1,eq3,eq2,A_comp[1],B[1]);
  and(lesser0,eq3,eq2,eq1,A_comp[0],B[0]);
  

  and(equal,eq0,eq1,eq2,eq3);
  or(greater,greater0,greater1,greater2,greater3);
  or(lesser,lesser0,lesser1,lesser2,lesser3);


endmodule

Verilog/fulladder.v
module fulladder(input A,input B,input C_in,output S,output C);
   wire S_inter;
   wire C_inter1;
   wire C_inter2;
   xor(S_inter,A,B);
   xor(S,S_inter,C_in);
   and(C_inter1,A,B);
   and(C_inter2,S_inter,C_in);
   or(C,C_inter1,C_inter2);

endmodule

Verilog/addersubtractor.v
`include "fulladder.v"
module addersubtractor(input M,input [3:0] A,input [3:0] B,output [3:0] S,output carry);
  wire [3:0] B_updated;
  xor(B_updated[3],B[3],M);
  xor(B_updated[2],B[2],M);
  xor(B_updated[1],B[1],M);
  xor(B_updated[0],B[0],M);
  wire C1;
  wire C2;
  wire C3;
  fulladder instance_1(.A(A[0]),.B(B_updated[0]),.C_in(M),.S(S[0]),.C(C1));
  fulladder instance_2(.A(A[1]),.B(B_updated[1]),.C_in(C1),.S(S[1]),.C(C2));
  fulladder instance_3(.A(A[2]),.B(B_updated[2]),.C_in(C2),.S(S[2]),.C(C3));
  fulladder instance_4(.A(A[3]),.B(B_updated[3]),.C_in(C3),.S(S[3]),.C(carry));
  
endmodule

Verilog/enableblock.v
module enableblock(input enable,input [3:0] A_in,input [3:0] B_in,output [3:0] A_out,output [3:0] B_out);
  and(A_out[3],A_in[3],enable);
  and(A_out[2],A_in[2],enable);
  and(A_out[1],A_in[1],enable);
   and(A_out[0],A_in[0],enable);
   and(B_out[3],B_in[3],enable);
  and(B_out[2],B_in[2],enable);
  and(B_out[1],B_in[1],enable);
  and(B_out[0],B_in[0],enable);
endmodule

Verilog/twotofourdecoder.v
module twotofourdecoder(input S0,input S1,output D0,output D1,output D2,output D3);
  wire S0_comp;
  wire S1_comp;
  not(S0_comp,S0);
  not(S1_comp,S1);
  and(D0,S0_comp,S1_comp);
  and(D1,S0,S1_comp);
  and(D2,S1,S0_comp);
  and(D3,S0,S1);
endmodule

Verilog/ALU_5output.v
`include "twotofourdecoder.v"
`include "enableblock.v"
`include "addersubtractor.v"
`include "comparator.v"
`include "andblock.v"
module ALU_5output(input S0,input S1,input [3:0] A,input [3:0] B,output [3:0] X,output carry);
   wire D0,D1,D2,D3;
   wire [3:0] S_0;
   wire carry_temp;
   wire [3:0] S_3;
   wire greater,lesser,equal;
   wire [3:0] A_0;
   wire [3:0] A_2;
   wire [3:0] A_3;
   wire [3:0] B_0;
   wire [3:0] B_2;
   wire [3:0] B_3;
  wire D_updated;

   twotofourdecoder instance_1(.S0(S0),.S1(S1),.D0(D0),.D1(D1),.D2(D2),.D3(D3));
   or(D_updated,D0,D1);
   enableblock inst_1(.enable(D_updated),.A_in(A),.B_in(B),.A_out(A_0),.B_out(B_0));
   enableblock inst_2(.enable(D2),.A_in(A),.B_in(B),.A_out(A_2),.B_out(B_2));
   enableblock inst_3(.enable(D3),.A_in(A),.B_in(B),.A_out(A_3),.B_out(B_3));
   addersubtractor inst_4(.M(S0),.A(A_0),.B(B_0),.S(S_0),.carry(carry_temp));
   comparator inst_5(.A(A_2),.B(B_2),.greater(greater),.lesser(lesser),.equal(equal));
   andblock inst_6(.A(A_3),.B(B_3),.C(S_3));
   wire equal_updated;
   and(equal_updated,equal,D2);
   or(X[0],greater,S_0[0],S_3[0]);
   or(X[1],equal_updated,S_0[1],S_3[1]);
   or(X[2],lesser,S_0[2],S_3[2]);
    or(X[3],S_0[3],S_3[3]);
    and(carry,carry_temp,D_updated);
endmodule

Verilog/ALU_5output_tb.v
module ALU_5output_tb;
  reg [3:0] A;
  reg [3:0] B;
  reg S0,S1;
  wire [3:0] Output;
  wire carry;
  ALU_5output DUT(S0,S1,A,B,Output,carry);
  
  initial begin
    $dumpfile("ALU_5output_tb.vcd");
    $dumpvars(0, ALU_5output_tb);
    S0=0;
    S1=0;
    A=4'b0101;
    B=4'b1001;
    #10
    S0=1;
    S1=0;
    A=4'b0100;
    B=4'b1011;
    #10
    S0=1;
    S1=1;
    A=4'b0110;
    B=4'b1111;
    #10
    S0=0;
    S1=1;
    A=4'b0110;
    B=4'b1101;
    #10
    S0=0;
    S1=1;
    A=4'b1000;
    B=4'b1000;
    #10
    S0=1;
    S1=1;
    A=4'b0101;
    B=4'b1100;
    #10
    S0=0;
    S1=0;
    A=4'b0000;
    B=4'b1100;
    #10
    S0=1;
    S1=1;
    A=4'b0011;
    B=4'b1100;
    #10
    S0=0;
    S1=1;
    A=4'b1011;
    B=4'b1010;

    #10 $finish; 
  end
endmodule

Verilog/ALU_5output_tb.vcd
$date
	Thu Nov  2 18:05:14 2023
$end
$version
	Icarus Verilog
$end
$timescale
	1s
$end
$scope module ALU_5output_tb $end
$var wire 1 ! carry $end
$var wire 4 " Output [3:0] $end
$var reg 4 # A [3:0] $end
$var reg 4 $ B [3:0] $end
$var reg 1 % S0 $end
$var reg 1 & S1 $end
$scope module DUT $end
$var wire 4 ' A [3:0] $end
$var wire 4 ( B [3:0] $end
$var wire 1 ) D_updated $end
$var wire 1 % S0 $end
$var wire 1 & S1 $end
$var wire 1 ! carry $end
$var wire 1 * equal_updated $end
$var wire 1 + lesser $end
$var wire 1 , greater $end
$var wire 1 - equal $end
$var wire 1 . carry_temp $end
$var wire 4 / X [3:0] $end
$var wire 4 0 S_3 [3:0] $end
$var wire 4 1 S_0 [3:0] $end
$var wire 1 2 D3 $end
$var wire 1 3 D2 $end
$var wire 1 4 D1 $end
$var wire 1 5 D0 $end
$var wire 4 6 B_3 [3:0] $end
$var wire 4 7 B_2 [3:0] $end
$var wire 4 8 B_0 [3:0] $end
$var wire 4 9 A_3 [3:0] $end
$var wire 4 : A_2 [3:0] $end
$var wire 4 ; A_0 [3:0] $end
$scope module inst_1 $end
$var wire 4 < A_in [3:0] $end
$var wire 4 = B_in [3:0] $end
$var wire 1 ) enable $end
$var wire 4 > B_out [3:0] $end
$var wire 4 ? A_out [3:0] $end
$upscope $end
$scope module inst_2 $end
$var wire 4 @ A_in [3:0] $end
$var wire 4 A B_in [3:0] $end
$var wire 1 3 enable $end
$var wire 4 B B_out [3:0] $end
$var wire 4 C A_out [3:0] $end
$upscope $end
$scope module inst_3 $end
$var wire 4 D A_in [3:0] $end
$var wire 4 E B_in [3:0] $end
$var wire 1 2 enable $end
$var wire 4 F B_out [3:0] $end
$var wire 4 G A_out [3:0] $end
$upscope $end
$scope module inst_4 $end
$var wire 4 H A [3:0] $end
$var wire 4 I B [3:0] $end
$var wire 1 % M $end
$var wire 1 . carry $end
$var wire 4 J S [3:0] $end
$var wire 1 K C3 $end
$var wire 1 L C2 $end
$var wire 1 M C1 $end
$var wire 4 N B_updated [3:0] $end
$scope module instance_1 $end
$var wire 1 O A $end
$var wire 1 P B $end
$var wire 1 M C $end
$var wire 1 % C_in $end
$var wire 1 Q C_inter1 $end
$var wire 1 R C_inter2 $end
$var wire 1 S S $end
$var wire 1 T S_inter $end
$upscope $end
$scope module instance_2 $end
$var wire 1 U A $end
$var wire 1 V B $end
$var wire 1 L C $end
$var wire 1 M C_in $end
$var wire 1 W C_inter1 $end
$var wire 1 X C_inter2 $end
$var wire 1 Y S $end
$var wire 1 Z S_inter $end
$upscope $end
$scope module instance_3 $end
$var wire 1 [ A $end
$var wire 1 \ B $end
$var wire 1 K C $end
$var wire 1 L C_in $end
$var wire 1 ] C_inter1 $end
$var wire 1 ^ C_inter2 $end
$var wire 1 _ S $end
$var wire 1 ` S_inter $end
$upscope $end
$scope module instance_4 $end
$var wire 1 a A $end
$var wire 1 b B $end
$var wire 1 . C $end
$var wire 1 K C_in $end
$var wire 1 c C_inter1 $end
$var wire 1 d C_inter2 $end
$var wire 1 e S $end
$var wire 1 f S_inter $end
$upscope $end
$upscope $end
$scope module inst_5 $end
$var wire 4 g A [3:0] $end
$var wire 4 h B [3:0] $end
$var wire 1 i eq0 $end
$var wire 1 j eq1 $end
$var wire 1 k eq2 $end
$var wire 1 l eq3 $end
$var wire 1 - equal $end
$var wire 1 , greater $end
$var wire 1 m greater0 $end
$var wire 1 n greater1 $end
$var wire 1 o greater2 $end
$var wire 1 p greater3 $end
$var wire 1 + lesser $end
$var wire 1 q lesser0 $end
$var wire 1 r lesser1 $end
$var wire 1 s lesser2 $end
$var wire 1 t lesser3 $end
$var wire 4 u B_comp [3:0] $end
$var wire 4 v A_comp [3:0] $end
$upscope $end
$scope module inst_6 $end
$var wire 4 w A [3:0] $end
$var wire 4 x B [3:0] $end
$var wire 4 y C [3:0] $end
$upscope $end
$scope module instance_1 $end
$var wire 1 5 D0 $end
$var wire 1 4 D1 $end
$var wire 1 3 D2 $end
$var wire 1 2 D3 $end
$var wire 1 % S0 $end
$var wire 1 z S0_comp $end
$var wire 1 & S1 $end
$var wire 1 { S1_comp $end
$upscope $end
$upscope $end
$upscope $end
$enddefinitions $end
#0
$dumpvars
1{
1z
b0 y
b0 x
b0 w
b1111 v
b1111 u
0t
0s
0r
0q
0p
0o
0n
0m
1l
1k
1j
1i
b0 h
b0 g
1f
1e
0d
0c
1b
0a
1`
1_
0^
0]
0\
1[
0Z
1Y
0X
0W
0V
0U
0T
0S
0R
1Q
1P
1O
b1001 N
1M
0L
0K
b1110 J
b1001 I
b101 H
b0 G
b0 F
b1001 E
b101 D
b0 C
b0 B
b1001 A
b101 @
b101 ?
b1001 >
b1001 =
b101 <
b101 ;
b0 :
b0 9
b1001 8
b0 7
b0 6
15
04
03
02
b1110 1
b0 0
b1110 /
0.
1-
0,
0+
0*
1)
b1001 (
b101 '
0&
0%
b1001 $
b101 #
b1110 "
0!
$end
#10
0L
0Y
0X
0_
1K
0R
0M
0O
0f
0`
1]
0Z
0T
0Q
b1001 "
b1001 /
b1011 8
b1011 >
b1011 I
b100 ;
b100 ?
b100 H
0b
1\
0V
0P
05
b100 N
b1001 1
b1001 J
1S
0z
14
b1011 $
b1011 (
b1011 =
b1011 A
b1011 E
b100 #
b100 '
b100 <
b100 @
b100 D
1%
#20
1.
0e
1d
1^
1L
1X
1M
0_
0S
1R
1f
1`
1T
1K
1b
1V
1P
0]
b110 "
b110 /
1\
b0 1
b0 J
0Y
0[
b1111 N
1Z
b110 0
b110 y
0U
0)
b0 8
b0 >
b0 I
b0 ;
b0 ?
b0 H
04
b1111 6
b1111 F
b1111 x
b110 9
b110 G
b110 w
0{
12
b1111 $
b1111 (
b1111 =
b1111 A
b1111 E
b110 #
b110 '
b110 <
b110 @
b110 D
1&
#30
1+
0-
0,
0.
0K
0i
0l
b10 u
1t
0j
0n
b1001 v
0o
0e
0d
0^
0L
b0 0
b0 y
0f
0`
0Z
0T
b100 "
b100 /
0Y
0X
b1101 7
b1101 B
b1101 h
b110 :
b110 C
b110 g
0*
0b
0\
0V
0P
0M
13
b0 6
b0 F
b0 x
b0 9
b0 G
b0 w
b0 N
b0 1
b0 J
0S
0R
1z
02
b1101 $
b1101 (
b1101 =
b1101 A
b1101 E
0%
#40
0+
b10 "
b10 /
0t
1*
1-
1i
b111 u
1l
1j
b111 v
b1000 7
b1000 B
b1000 h
b1000 :
b1000 C
b1000 g
b1000 $
b1000 (
b1000 =
b1000 A
b1000 E
b1000 #
b1000 '
b1000 <
b1000 @
b1000 D
#50
1.
1d
1K
1^
1L
1X
1M
b1111 u
b1111 v
0e
0_
0Y
1R
b100 0
b100 y
1f
1`
1Z
1T
b100 "
b100 /
b0 7
b0 B
b0 h
0*
b0 :
b0 C
b0 g
1b
1\
1V
1P
03
b1100 6
b1100 F
b1100 x
b101 9
b101 G
b101 w
b1111 N
b0 1
b0 J
0S
0z
12
b1100 $
b1100 (
b1100 =
b1100 A
b1100 E
b101 #
b101 '
b101 <
b101 @
b101 D
1%
#60
1_
0.
0K
1e
0d
0^
0L
0!
b1100 8
b1100 >
b1100 I
b0 0
b0 y
1f
1`
0Z
0T
b1100 "
b1100 /
0Y
0X
1)
1b
1\
0V
0P
0M
15
b0 6
b0 F
b0 x
b0 9
b0 G
b0 w
1{
b1100 N
b1100 1
b1100 J
0S
0R
1z
02
b0 #
b0 '
b0 <
b0 @
b0 D
0&
0%
#70
1.
1d
1K
1^
1X
1L
1M
0W
0Q
0e
0_
0Y
1R
b0 8
b0 >
b0 I
0U
0O
1f
1`
1Z
1T
b0 "
b0 /
0)
b0 ;
b0 ?
b0 H
1b
1\
1V
1P
05
b1100 6
b1100 F
b1100 x
b11 9
b11 G
b11 w
0{
b1111 N
b0 1
b0 J
0S
0z
04
12
b11 #
b11 '
b11 <
b11 @
b11 D
1&
1%
#80
0-
1m
0+
1,
0.
0K
0t
0i
0n
b101 u
0r
b100 v
0p
0e
0d
0^
0L
0f
0`
0Z
0T
b1 "
b1 /
0Y
0X
0*
b1010 7
b1010 B
b1010 h
b1011 :
b1011 C
b1011 g
0b
0\
0V
0P
0M
13
b0 6
b0 F
b0 x
b0 9
b0 G
b0 w
b0 N
b0 1
b0 J
0S
0R
1z
02
b1010 $
b1010 (
b1010 =
b1010 A
b1010 E
b1011 #
b1011 '
b1011 <
b1011 @
b1011 D
0%
