Verilog/andblock.v
module andblock(input [3:0] A,input [3:0] B,output [3:0] C);
  and(C[3],A[3],B[3]);
  and(C[2],A[2],B[2]);
  and(C[1],A[1],B[1]);
  and(C[0],A[0],B[0]);
endmodule

Verilog/andblock_tb.v
`include "andblock.v"
module andblock_tb;
  reg [3:0] A;
  reg [3:0] B;
  wire [3:0] C;
  andblock DUT(A,B,C);
  
   initial begin
    $dumpfile("andblock_tb.vcd");
    $dumpvars(0, andblock_tb);
    
    A=4'b0101;
    B=4'b1001;
    #10
   
    A=4'b0100;
    B=4'b1011;
    #10
   
    A=4'b0000;
    B=4'b1111;
    #10
    
    A=4'b0110;
    B=4'b1101;
    #10
    
    A=4'b1000;
    B=4'b1000;
    #10
  
    A=4'b0101;
    B=4'b1100;
    #10

    A=4'b0000;
    B=4'b1011;
    #10

    A=4'b0011;
    B=4'b1100;

    #10 $finish; 
  end
  
endmodule

Verilog/andblock_tb.vcd
$date
	Mon Nov  6 19:45:06 2023
$end
$version
	Icarus Verilog
$end
$timescale
	1s
$end
$scope module andblock_tb $end
$var wire 4 ! C [3:0] $end
$var reg 4 " A [3:0] $end
$var reg 4 # B [3:0] $end
$scope module DUT $end
$var wire 4 $ A [3:0] $end
$var wire 4 % B [3:0] $end
$var wire 4 & C [3:0] $end
$upscope $end
$upscope $end
$enddefinitions $end
#0
$dumpvars
b1 &
b1001 %
b101 $
b1001 #
b101 "
b1 !
$end
#10
b0 !
b0 &
b1011 #
b1011 %
b100 "
b100 $
#20
b1111 #
b1111 %
b0 "
b0 $
#30
b100 !
b100 &
b1101 #
b1101 %
b110 "
b110 $
#40
b1000 !
b1000 &
b1000 #
b1000 %
b1000 "
b1000 $
#50
b100 !
b100 &
b1100 #
b1100 %
b101 "
b101 $
#60
b0 !
b0 &
b1011 #
b1011 %
b0 "
b0 $
#70
b1100 #
b1100 %
b11 "
b11 $
