Verilog/comparator.v
module comparator(input [3:0] A,input [3:0] B,output greater,output lesser,output equal);
  wire eq0;
  wire eq1;
  wire eq2;
  wire eq3;
  xnor(eq0,A[0],B[0]);
  xnor(eq1,A[1],B[1]);
  xnor(eq2,A[2],B[2]);
  xnor(eq3,A[3],B[3]);

  
  wire [3:0] A_comp;
  wire [3:0] B_comp;
  not(A_comp[3],A[3]);
  not(A_comp[2],A[2]);
  not(A_comp[1],A[1]);
  not(A_comp[0],A[0]);
  not(B_comp[3],B[3]);
  not(B_comp[2],B[2]);
  not(B_comp[1],B[1]);
  not(B_comp[0],B[0]);


  wire greater0;
  wire greater1;
  wire greater2;
  wire greater3;
  and(greater3,A[3],B_comp[3]);
  and(greater2,eq3,A[2],B_comp[2]);
  and(greater1,eq3,eq2,A[1],B_comp[1]);
  and(greater0,eq3,eq2,eq1,A[0],B_comp[0]);

 
  wire lesser0;
  wire lesser1;
  wire lesser2;
  wire lesser3;
  and(lesser3,A_comp[3],B[3]);
  and(lesser2,eq3,A_comp[2],B[2]);
  and(lesser1,eq3,eq2,A_comp[1],B[1]);
  and(lesser0,eq3,eq2,eq1,A_comp[0],B[0]);
  

  and(equal,eq0,eq1,eq2,eq3);
  or(greater,greater0,greater1,greater2,greater3);
  or(lesser,lesser0,lesser1,lesser2,lesser3);


endmodule

Verilog/comparator_tb.v
`include "comparator.v"
module comparator_tb;
  reg [3:0] A;
  reg [3:0] B;
  wire greater,lesser,equal;
  comparator DUT(A,B,greater,lesser,equal);
  
  
  initial begin
    $dumpfile("comparator_tb.vcd");
    $dumpvars(0, comparator_tb);
    
    A=4'b0101;
    B=4'b1001;
    #10
   
    A=4'b1011;
    B=4'b1011;
    #10
   
    A=4'B1011;
    B=4'b1111;
    #10
    
    A=4'b1001;
    B=4'b0110;
    #10
    
    A=4'b1111;
    B=4'b1111;
    #10
  
    A=4'b0100;
    B=4'b1100;
    #10

    A=4'b1110;
    B=4'b0000;
    #10

    A=4'b0011;
    B=4'b1100;

    #10 $finish; 
  end
  
endmodule

Verilog/comparator_tb.vcd
$date
	Mon Nov  6 19:42:50 2023
$end
$version
	Icarus Verilog
$end
$timescale
	1s
$end
$scope module comparator_tb $end
$var wire 1 ! lesser $end
$var wire 1 " greater $end
$var wire 1 # equal $end
$var reg 4 $ A [3:0] $end
$var reg 4 % B [3:0] $end
$scope module DUT $end
$var wire 4 & A [3:0] $end
$var wire 4 ' B [3:0] $end
$var wire 1 ( eq0 $end
$var wire 1 ) eq1 $end
$var wire 1 * eq2 $end
$var wire 1 + eq3 $end
$var wire 1 # equal $end
$var wire 1 " greater $end
$var wire 1 , greater0 $end
$var wire 1 - greater1 $end
$var wire 1 . greater2 $end
$var wire 1 / greater3 $end
$var wire 1 ! lesser $end
$var wire 1 0 lesser0 $end
$var wire 1 1 lesser1 $end
$var wire 1 2 lesser2 $end
$var wire 1 3 lesser3 $end
$var wire 4 4 B_comp [3:0] $end
$var wire 4 5 A_comp [3:0] $end
$upscope $end
$upscope $end
$enddefinitions $end
#0
$dumpvars
b1010 5
b110 4
13
02
01
00
0/
0.
0-
0,
0+
0*
1)
1(
b1001 '
b101 &
b1001 %
b101 $
0#
0"
1!
$end
#10
0!
0"
03
0-
1#
b100 4
01
1*
1+
b100 5
b1011 %
b1011 '
b1011 $
b1011 &
#20
0#
1!
0*
b0 4
12
b1111 %
b1111 '
#30
1"
0!
1/
02
0(
0+
b1001 4
0)
b110 5
b110 %
b110 '
b1001 $
b1001 &
#40
0"
0/
0,
1#
1(
1+
b0 4
1)
1*
b0 5
b1111 %
b1111 '
b1111 $
b1111 &
#50
1!
13
0#
b11 4
0+
b1011 5
b1100 %
b1100 '
b100 $
b100 &
#60
1"
1/
0!
0*
b1111 4
03
0)
b1 5
b0 %
b0 '
b1110 $
b1110 &
#70
1!
13
0"
b11 4
0(
b1100 5
0/
b1100 %
b1100 '
b11 $
b11 &
