Verilog/fulladder.v
module fulladder(input A,input B,input C_in,output S,output C);
   wire S_inter;
   wire C_inter1;
   wire C_inter2;
   xor(S_inter,A,B);
   xor(S,S_inter,C_in);
   and(C_inter1,A,B);
   and(C_inter2,S_inter,C_in);
   or(C,C_inter1,C_inter2);

endmodule

Verilog/fulladder_tb.v
`include "fulladder.v"
module fulladder_tb;
  reg A,B,C_in;
  wire S,C;
  fulladder DUT(A,B,C_in,S,C);
  
  integer i;
  
  initial begin
    $dumpfile("fulladder_tb.vcd");
    $dumpvars(0, fulladder_tb);
    A=1'b0;  B=1'b0;  
    C_in=1'b0;
    for (i = 0; i < 8; i = i + 1) begin
       #1
       {C_in,B,A}=i;
       
    end
    
    #1 $finish;
  end
  
endmodule

Verilog/fulladder_tb.vcd
$date
	Mon Nov  6 19:53:37 2023
$end
$version
	Icarus Verilog
$end
$timescale
	1s
$end
$scope module fulladder_tb $end
$var wire 1 ! S $end
$var wire 1 " C $end
$var reg 1 # A $end
$var reg 1 $ B $end
$var reg 1 % C_in $end
$var integer 32 & i [31:0] $end
$scope module DUT $end
$var wire 1 # A $end
$var wire 1 $ B $end
$var wire 1 " C $end
$var wire 1 % C_in $end
$var wire 1 ' C_inter1 $end
$var wire 1 ( C_inter2 $end
$var wire 1 ! S $end
$var wire 1 ) S_inter $end
$upscope $end
$upscope $end
$enddefinitions $end
#0
$dumpvars
0)
0(
0'
b0 &
0%
0$
0#
0"
0!
$end
#1
b1 &
#2
1!
1)
b10 &
1#
#3
b11 &
1$
0#
#4
0!
1"
0)
1'
b100 &
1#
#5
0"
1!
0'
b101 &
1%
0$
0#
#6
1"
0!
1(
1)
b110 &
1#
#7
b111 &
1$
0#
#8
1!
0(
0)
1'
b1000 &
1#
